pytablewriter/__init__.py
pytablewriter/__version__.py
pytablewriter/_converter.py
pytablewriter/_factory.py
pytablewriter/_function.py
pytablewriter/_table_format.py
pytablewriter/_typing.py
pytablewriter/error.py
pytablewriter/py.typed
pytablewriter/_logger/__init__.py
pytablewriter/_logger/_logger.py
pytablewriter/_logger/_null_logger.py
pytablewriter/sanitizer/__init__.py
pytablewriter/sanitizer/_base.py
pytablewriter/sanitizer/_elasticsearch.py
pytablewriter/sanitizer/_excel.py
pytablewriter/sanitizer/_interface.py
pytablewriter/sanitizer/_javascript.py
pytablewriter/sanitizer/_python.py
pytablewriter/style/__init__.py
pytablewriter/style/_cell.py
pytablewriter/style/_font.py
pytablewriter/style/_style.py
pytablewriter/style/_styler.py
pytablewriter/style/_styler_interface.py
pytablewriter/style/_theme.py
pytablewriter/typehint/__init__.py
pytablewriter/writer/__init__.py
pytablewriter/writer/_common.py
pytablewriter/writer/_elasticsearch.py
pytablewriter/writer/_interface.py
pytablewriter/writer/_msgfy.py
pytablewriter/writer/_null.py
pytablewriter/writer/_table_writer.py
pytablewriter/writer/binary/__init__.py
pytablewriter/writer/binary/_excel.py
pytablewriter/writer/binary/_excel_workbook.py
pytablewriter/writer/binary/_interface.py
pytablewriter/writer/binary/_pandas.py
pytablewriter/writer/binary/_sqlite.py
pytablewriter/writer/text/__init__.py
pytablewriter/writer/text/_asciidoc.py
pytablewriter/writer/text/_borderless.py
pytablewriter/writer/text/_common.py
pytablewriter/writer/text/_css.py
pytablewriter/writer/text/_csv.py
pytablewriter/writer/text/_html.py
pytablewriter/writer/text/_interface.py
pytablewriter/writer/text/_json.py
pytablewriter/writer/text/_jsonlines.py
pytablewriter/writer/text/_latex.py
pytablewriter/writer/text/_ltsv.py
pytablewriter/writer/text/_markdown.py
pytablewriter/writer/text/_mediawiki.py
pytablewriter/writer/text/_rst.py
pytablewriter/writer/text/_spacealigned.py
pytablewriter/writer/text/_text_writer.py
pytablewriter-1.2.0.dist-info/LICENSE
pytablewriter-1.2.0.dist-info/METADATA
pytablewriter-1.2.0.dist-info/WHEEL
pytablewriter-1.2.0.dist-info/top_level.txt
pytablewriter-1.2.0.dist-info/RECORD
