Metadata-Version: 2.1
Name: pytablewriter
Version: 1.2.0
Summary: pytablewriter is a Python library to write a table in various formats: AsciiDoc / CSV / Elasticsearch / HTML / JavaScript / JSON / LaTeX / LDJSON / LTSV / Markdown / MediaWiki / NumPy / Excel / Pandas / Python / reStructuredText / SQLite / TOML / TSV / YAML.
Home-page: https://github.com/thombashi/pytablewriter
Author: Tsuyoshi Hombashi
Author-email: tsuyoshi.hombashi@gmail.com
License: MIT License
Project-URL: Changlog, https://github.com/thombashi/pytablewriter/releases
Project-URL: Documentation, https://pytablewriter.rtfd.io/
Project-URL: Funding, https://github.com/sponsors/thombashi
Project-URL: Source, https://github.com/thombashi/pytablewriter
Project-URL: Tracker, https://github.com/thombashi/pytablewriter/issues
Keywords: AsciiDoc,table,CSV,Excel,JavaScript,JSON,LaTeX,LTSV,Markdown,MediaWiki,HTML,pandas,reStructuredText,SQLite,TSV,TOML
Classifier: Development Status :: 5 - Production/Stable
Classifier: Intended Audience :: Developers
Classifier: Intended Audience :: Information Technology
Classifier: License :: OSI Approved :: MIT License
Classifier: Operating System :: OS Independent
Classifier: Programming Language :: Python :: 3
Classifier: Programming Language :: Python :: 3.7
Classifier: Programming Language :: Python :: 3.8
Classifier: Programming Language :: Python :: 3.9
Classifier: Programming Language :: Python :: 3.10
Classifier: Programming Language :: Python :: 3.11
Classifier: Programming Language :: Python :: 3.12
Classifier: Programming Language :: Python :: 3 :: Only
Classifier: Programming Language :: Python :: Implementation :: CPython
Classifier: Programming Language :: Python :: Implementation :: PyPy
Classifier: Topic :: Software Development :: Code Generators
Classifier: Topic :: Software Development :: Libraries
Classifier: Topic :: Software Development :: Libraries :: Python Modules
Classifier: Topic :: Text Processing
Classifier: Topic :: Text Processing :: Markup :: HTML
Classifier: Topic :: Text Processing :: Markup :: LaTeX
Classifier: Topic :: Text Processing :: Markup :: Markdown
Classifier: Topic :: Text Processing :: Markup :: reStructuredText
Classifier: Typing :: Typed
Requires-Python: >=3.7
License-File: LICENSE
Requires-Dist: setuptools>=38.3.0
Requires-Dist: DataProperty<2,>=1.0.1
Requires-Dist: mbstrdecoder<2,>=1.0.0
Requires-Dist: pathvalidate<4,>=2.3.0
Requires-Dist: tabledata<2,>=1.3.1
Requires-Dist: tcolorpy<1,>=0.0.5
Requires-Dist: typepy[datetime]<2,>=1.3.2
Provides-Extra: all
Requires-Dist: xlwt; extra == "all"
Requires-Dist: XlsxWriter<4,>=0.9.6; extra == "all"
Requires-Dist: elasticsearch<9,>=8.0.1; extra == "all"
Requires-Dist: pytablereader<2,>=0.31.3; extra == "all"
Requires-Dist: dominate<3,>=2.1.5; extra == "all"
Requires-Dist: loguru<1,>=0.4.1; extra == "all"
Requires-Dist: SimpleSQLite<2,>=1.3.2; extra == "all"
Requires-Dist: pytablewriter-altrow-theme<1,>=0.2.0; extra == "all"
Requires-Dist: pytablewriter-altcol-theme<1,>=0.1.0; extra == "all"
Requires-Dist: toml<1,>=0.9.3; extra == "all"
Requires-Dist: PyYAML<7,>=3.11; extra == "all"
Requires-Dist: simplejson<4,>=3.8.1; extra == "all"
Requires-Dist: pandas<3,>=0.25.3; extra == "all"
Provides-Extra: docs
Requires-Dist: sphinx_rtd_theme>=1.2.2; extra == "docs"
Requires-Dist: Sphinx>=2.4; extra == "docs"
Requires-Dist: xlwt; extra == "docs"
Requires-Dist: XlsxWriter<4,>=0.9.6; extra == "docs"
Requires-Dist: elasticsearch<9,>=8.0.1; extra == "docs"
Requires-Dist: pytablereader<2,>=0.31.3; extra == "docs"
Requires-Dist: dominate<3,>=2.1.5; extra == "docs"
Requires-Dist: loguru<1,>=0.4.1; extra == "docs"
Requires-Dist: SimpleSQLite<2,>=1.3.2; extra == "docs"
Requires-Dist: pytablewriter-altrow-theme<1,>=0.2.0; extra == "docs"
Requires-Dist: pytablewriter-altcol-theme<1,>=0.1.0; extra == "docs"
Requires-Dist: toml<1,>=0.9.3; extra == "docs"
Requires-Dist: PyYAML<7,>=3.11; extra == "docs"
Requires-Dist: simplejson<4,>=3.8.1; extra == "docs"
Requires-Dist: pandas<3,>=0.25.3; extra == "docs"
Provides-Extra: es
Requires-Dist: elasticsearch<9,>=8.0.1; extra == "es"
Provides-Extra: es8
Requires-Dist: elasticsearch<9,>=8.0.1; extra == "es8"
Provides-Extra: excel
Requires-Dist: xlwt; extra == "excel"
Requires-Dist: XlsxWriter<4,>=0.9.6; extra == "excel"
Provides-Extra: from
Requires-Dist: pytablereader<2,>=0.31.3; extra == "from"
Provides-Extra: html
Requires-Dist: dominate<3,>=2.1.5; extra == "html"
Provides-Extra: logging
Requires-Dist: loguru<1,>=0.4.1; extra == "logging"
Provides-Extra: pandas
Requires-Dist: pandas<3,>=0.25.3; extra == "pandas"
Provides-Extra: sqlite
Requires-Dist: SimpleSQLite<2,>=1.3.2; extra == "sqlite"
Provides-Extra: test
Requires-Dist: pandas<3,>=0.25.3; extra == "test"
Requires-Dist: XlsxWriter<4,>=0.9.6; extra == "test"
Requires-Dist: beautifulsoup4>=4.10; extra == "test"
Requires-Dist: toml<1,>=0.9.3; extra == "test"
Requires-Dist: pytablewriter-altcol-theme<1,>=0.1.0; extra == "test"
Requires-Dist: pytest-md-report>=0.4.1; extra == "test"
Requires-Dist: pytablereader<2,>=0.31.3; extra == "test"
Requires-Dist: SimpleSQLite<2,>=1.3.2; extra == "test"
Requires-Dist: dominate<3,>=2.1.5; extra == "test"
Requires-Dist: pytablewriter-altrow-theme<1,>=0.2.0; extra == "test"
Requires-Dist: loguru<1,>=0.4.1; extra == "test"
Requires-Dist: xlwt; extra == "test"
Requires-Dist: PyYAML<7,>=3.11; extra == "test"
Requires-Dist: elasticsearch<9,>=8.0.1; extra == "test"
Requires-Dist: tablib>=3.2.0; extra == "test"
Requires-Dist: pytablereader[excel,sqlite]>=0.31.3; extra == "test"
Requires-Dist: simplejson<4,>=3.8.1; extra == "test"
Requires-Dist: sqliteschema>=1.3.0; extra == "test"
Requires-Dist: pytest>=6.0.1; extra == "test"
Provides-Extra: theme
Requires-Dist: pytablewriter-altrow-theme<1,>=0.2.0; extra == "theme"
Requires-Dist: pytablewriter-altcol-theme<1,>=0.1.0; extra == "theme"
Provides-Extra: toml
Requires-Dist: toml<1,>=0.9.3; extra == "toml"
Provides-Extra: yaml
Requires-Dist: PyYAML<7,>=3.11; extra == "yaml"
